{
  "context-menu": {
    ".tree-view": [
      {
        "label": "Sync-Sync",
        "submenu": [
          {
            "label": "Import/Export",
            "command": "sync-sync:openMainView"
          },
          {
            "label": "Rename with Syncing",
            "command": "sync-sync:rename"
          },
          {
            "label": "Delete with Syncing",
            "command": "sync-sync:delete"
          },
          {
            "label": "Settings",
            "command": "sync-sync:openSettingsView"
          }
        ]
      }
    ]
  },
  "menu": [
    {
      "label": "Packages",
      "submenu": [
        {
          "label": "Sync-Sync",
          "submenu": [
            {
              "label": "Settings",
              "command": "sync-sync:openSettingsView"
            }
          ]
        }
      ]
    }
  ]
}
